safe_init/__init__.py
safe_init/decorator.py
safe_init/dlq.py
safe_init/environment.py
safe_init/error_utils.py
safe_init/errors.py
safe_init/handler.py
safe_init/py.typed
safe_init/safe_logging.py
safe_init/secrets.py
safe_init/sentry.py
safe_init/slack.py
safe_init/timeout.py
safe_init/tracer.py
safe_init/utils.py
safe_init-1.4.0.dist-info/METADATA
safe_init-1.4.0.dist-info/WHEEL
safe_init-1.4.0.dist-info/licenses/LICENSE
safe_init-1.4.0.dist-info/RECORD
