Metadata-Version: 2.4
Name: safe-init
Version: 1.4.0
Summary: Safe Init is a Python library that enhances AWS Lambda functions with advanced error handling, logging, monitoring, and resilience features, providing comprehensive observability and reliability for serverless applications.
Project-URL: Repository, https://github.com/kalepa/safe-init
Project-URL: Documentation, https://safe-init.readthedocs.io/en/latest/
Author-email: Maciej Wilczyński <maciej@lupine.software>
License-Expression: MIT
License-File: LICENSE
Classifier: Development Status :: 5 - Production/Stable
Classifier: Intended Audience :: Developers
Classifier: License :: OSI Approved :: MIT License
Classifier: Operating System :: OS Independent
Classifier: Programming Language :: Python
Classifier: Programming Language :: Python :: 3.11
Classifier: Topic :: Software Development :: Libraries
Classifier: Topic :: Software Development :: Libraries :: Python Modules
Classifier: Topic :: System :: Logging
Classifier: Topic :: System :: Monitoring
Classifier: Typing :: Typed
Requires-Python: <3.12,>=3.11
Requires-Dist: awslambdaric>=2.0.10
Requires-Dist: boto3-type-annotations>=0.3.1
Requires-Dist: boto3>=1.20.0
Requires-Dist: datadog-lambda
Requires-Dist: ddtrace
Requires-Dist: redis<6,>=4.0.0
Requires-Dist: requests<3,>=2.31.0
Requires-Dist: sentry-sdk<2.0.0
Requires-Dist: structlog<25,>=24.1.0
